bcp_realtime/__init__.py
bcp_realtime/bcp_realtime.py
bcp_realtime/history_tracker.py
bcp_realtime/mini_viewer.py
bcp_realtime-1.0.0b2.dist-info/LICENSE
bcp_realtime-1.0.0b2.dist-info/METADATA
bcp_realtime-1.0.0b2.dist-info/WHEEL
bcp_realtime-1.0.0b2.dist-info/top_level.txt
bcp_realtime-1.0.0b2.dist-info/RECORD
