Metadata-Version: 2.1
Name: bcp-realtime
Version: 1.0.0b2
Summary: A package to interact/read the bcp (BCP GmbH) data
Author-email: Jonathan Krüger <pinguin@lagerfeuerhacker.de>
License: GNU GENERAL PUBLIC LICENSE
Project-URL: Repository, https://edugit.org/pinguin/bcp-realtime.git
Project-URL: Homepage, https://edugit.org/pinguin/bcp-realtime
Project-URL: Bug Tracker, https://edugit.org/pinguin/bcp-realtime/-/issues
Keywords: bcp,BCP Bonn,realtime,opendata,bonn,parking
Classifier: Programming Language :: Python :: 3
Requires-Python: >=3.7
License-File: LICENSE
Requires-Dist: requests
Requires-Dist: xmltodict
